{
  "components/features/layout-1.html": {
    "status": "ok",
    "mobileStatus": "fail",
    "checkedAt": "2026-03-10",
    "note": "Desktop ok; mobile tekst afgekapt/overflow."
  },
  "components/features/layout-15.html": {
    "status": "warn",
    "mobileStatus": "fail",
    "checkedAt": "2026-03-10",
    "note": "Desktop broken icons; mobiel heading/text overflow en broken images."
  },
  "components/features/layout-50.html": {
    "status": "ok",
    "checkedAt": "2026-03-11",
    "desktop": "ok",
    "mobile": "ok",
    "note": "gefixed: herschreven met CDN Tailwind, volledige feature layout met text/image/feature list"
  },
  "components/hero-headers-new/header-1.html": {
    "status": "ok",
    "checkedAt": "2026-03-11",
    "desktop": "ok",
    "mobile": "ok",
    "note": "gefixed: herschreven met CDN Tailwind, responsive 2-koloms hero met heading/tekst/knoppen"
  },
  "components/hero-headers-new/header-5.html": {
    "status": "ok",
    "checkedAt": "2026-03-11",
    "desktop": "ok",
    "mobile": "ok",
    "note": "gefixed: herschreven met CDN Tailwind, full-width hero met overlay tekst/knoppen"
  },
  "components/cta-new/cta-1.html": {
    "status": "ok",
    "mobileStatus": "fail",
    "checkedAt": "2026-03-10",
    "note": "Desktop goed; mobiel tekst rechts afgekapt."
  },
  "components/cta-new/cta-5.html": {
    "status": "ok",
    "mobileStatus": "ok",
    "checkedAt": "2026-03-10",
    "note": "Leesbare dark CTA met gestijlde knoppen op desktop en mobiel."
  },
  "components/banners/banner-1.html": {
    "status": "ok",
    "mobileStatus": "warn",
    "checkedAt": "2026-03-10",
    "note": "Desktop ok; mobiel veel lege ruimte en placeholder-iconen."
  },
  "components/banners/banner-8.html": {
    "status": "ok",
    "mobileStatus": "ok",
    "checkedAt": "2026-03-10",
    "note": "Compacte banner met correcte typografie en knoppen."
  },
  "components/footers/footer-1.html": {
    "status": "warn",
    "mobileStatus": "warn",
    "checkedAt": "2026-03-10",
    "note": "Footer aanwezig, maar meerdere icon/input placeholders tonen als lege cirkels."
  },
  "components/footers/footer-6.html": {
    "status": "ok",
    "mobileStatus": "warn",
    "checkedAt": "2026-03-10",
    "note": "Desktop goed; mobiel placeholders i.p.v. icon/input."
  },
  "components/navbars/navbar-1.html": {
    "status": "ok",
    "mobileStatus": "warn",
    "checkedAt": "2026-03-10",
    "note": "Desktop netjes; mobiel minimale inhoud met lege cirkel-placeholders."
  },
  "components/gallery/gallery-1.html": {
    "status": "ok",
    "checkedAt": "2026-03-11",
    "desktop": "ok",
    "mobile": "ok",
    "note": "gefixed: herschreven met CDN Tailwind, responsive 3-koloms gallery grid met 6 placeholders"
  },
  "components/logos/logo-1.html": {
    "status": "ok",
    "checkedAt": "2026-03-11",
    "desktop": "ok",
    "mobile": "ok",
    "note": "gefixed: CDN Tailwind, flex-wrap logo rij met brand-namen"
  },
  "components/timelines/timeline-1.html": {
    "status": "ok",
    "checkedAt": "2026-03-11",
    "desktop": "ok",
    "mobile": "ok",
    "note": "gefixed: herschreven met CDN Tailwind, timeline met dot/line indicator, min-w-0 op content, geen vaste w-96"
  },
  "components/event-sections/event-1.html": {
    "status": "ok",
    "mobileStatus": "warn",
    "checkedAt": "2026-03-10",
    "note": "Desktop goed; mobiel met afgekapt label en veel lege ruimte onderaan."
  },
  "components/blog-sections/blog-33.html": {
    "status": "ok",
    "mobileStatus": "ok",
    "checkedAt": "2026-03-10",
    "note": "Blog-sectie rendert correct; tabs/CTA zichtbaar."
  },
  "components/blog-sections/blog-37.html": {
    "status": "ok",
    "checkedAt": "2026-03-11",
    "desktop": "ok",
    "mobile": "ok",
    "note": "gefixed: CDN Tailwind, CTA button width fixed (w-1/12 \u2192 auto), button text kleur wit"
  },
  "components/contact/contact-1.html": {
    "status": "warn",
    "mobileStatus": "warn",
    "checkedAt": "2026-03-10",
    "note": "Contactformulier zichtbaar, maar meerdere velden renderen als icon placeholders."
  },
  "components/team/team-1.html": {
    "status": "warn",
    "mobileStatus": "warn",
    "checkedAt": "2026-03-10",
    "note": "Structuur aanwezig maar veel placeholder/afgekapt label en lege ruimte."
  },
  "components/faq/faq-1.html": {
    "status": "warn",
    "mobileStatus": "warn",
    "checkedAt": "2026-03-10",
    "note": "FAQ zichtbaar; accordions/open state en tekstuitlijning suboptimaal."
  },
  "components/stats-sections/stats-1.html": {
    "status": "warn",
    "mobileStatus": "warn",
    "checkedAt": "2026-03-10",
    "note": "Content zichtbaar maar labels afgekapt en visuele afwerking matig."
  },
  "components/portfolio-sections/portfolio-1.html": {
    "status": "warn",
    "mobileStatus": "warn",
    "checkedAt": "2026-03-10",
    "note": "Slechts beperkte card-content zichtbaar met placeholder image."
  },
  "components/careers/career-1.html": {
    "status": "ok",
    "mobileStatus": "warn",
    "checkedAt": "2026-03-10",
    "note": "Desktop ok; mobiel afgekapt label en accordion-tekst buiten container."
  },
  "components/pricing/pricing-1.html": {
    "status": "ok",
    "mobileStatus": "warn",
    "checkedAt": "2026-03-10",
    "note": "Desktop pricingkaart goed; mobiel krappe kolombreedte/tekst tegen rand."
  },
  "components/pricing/pricing-5.html": {
    "status": "warn",
    "mobileStatus": "ok",
    "checkedAt": "2026-03-10",
    "note": "Desktop onderzijde deels afgesneden; mobiel acceptabel."
  },
  "components/stat-cards/stat-card-1.html": {
    "status": "ok",
    "checkedAt": "2026-03-11",
    "desktop": "ok",
    "mobile": "ok",
    "note": "gefixed: herschreven met CDN Tailwind, 4 stat cards + header row + filter tabs"
  },
  "components/headers/header-44.html": {
    "status": "warn",
    "mobileStatus": "ok",
    "checkedAt": "2026-03-10",
    "note": "Desktop veel lege ruimte; mobiel leesbaar."
  },
  "components/pages/features/layout-79.html": {
    "status": "warn",
    "checkedAt": "2026-03-11",
    "note": "Placeholder-tekst aanwezig, Relume-logo overgedimensioneerd/afgesneden, geen knoppen."
  },
  "components/navbars/navbar-11.html": {
    "status": "ok",
    "checkedAt": "2026-03-11",
    "desktop": "ok",
    "mobile": "ok",
    "note": "gefixed: ongeldige gap-158 class verwijderd, navbar herschreven met logo/nav/CTA"
  },
  "components/contact-pages/contact-2.html": {
    "status": "ok",
    "checkedAt": "2026-03-11",
    "note": "Navbar, gestijlde knoppen en tabs renderen correct. Structureel in orde."
  },
  "components/features/layout-316.html": {
    "status": "ok",
    "checkedAt": "2026-03-11",
    "desktop": "ok",
    "mobile": "ok",
    "note": "gefixed: CDN Tailwind, 2-koloms layout met placeholder image en knoppen"
  },
  "components/pricing/pricing-49.html": {
    "status": "warn",
    "checkedAt": "2026-03-11",
    "note": "Heading en toggle renderen goed, pricing-cards/content onder tabs ontbreekt, tagline afgekort."
  },
  "components/style-guide/style-guide/icons.html": {
    "status": "ok",
    "checkedAt": "2026-03-11",
    "desktop": "ok",
    "mobile": "ok",
    "note": "gefixed: CDN Tailwind, inline SVG Heroicons aanwezig per card"
  },
  "components/application/topbars/topbar-sits-above-a-level-1-sidebar-includes-a-company-logo-but-does-not-have-nav-links.html": {
    "status": "ok",
    "checkedAt": "2026-03-11",
    "desktop": "ok",
    "mobile": "ok",
    "note": "gefixed: CDN Tailwind, topbar met sidebar shell correct gestyled"
  },
  "components/stats-sections/stats-37.html": {
    "status": "warn",
    "checkedAt": "2026-03-11",
    "note": "Tagline afgekort, heading en knoppen correct gestyled, lege ruimte onder tabs suggereert ontbrekende content."
  },
  "components/features/layout-258.html": {
    "status": "ok",
    "checkedAt": "2026-03-11",
    "desktop": "ok",
    "mobile": "ok",
    "note": "gefixed: CDN Tailwind, dark themed tabs/content aanwezig en leesbaar"
  },
  "components/gallery/gallery-25.html": {
    "status": "ok",
    "checkedAt": "2026-03-11",
    "note": "Nordvik branding, hero-sectie met achtergrond, heading en CTA-knoppen correct gerenderd."
  },
  "components/team/team-12.html": {
    "status": "warn",
    "checkedAt": "2026-03-11",
    "note": "Header en View-all knop correct, maar content-area onder tabs leeg - teamleden ontbreken."
  },
  "components/features/layout-126.html": {
    "status": "ok",
    "checkedAt": "2026-03-11",
    "note": "Schedule-layout netjes: tagline, heading, datum-tabs en tijdslot-rijen correct zichtbaar."
  },
  "components/pages/features/layout-258.html": {
    "status": "warn",
    "checkedAt": "2026-03-11",
    "note": "Tekst correct, maar oversized Relume-logo domineert viewport als placeholder image."
  },
  "components/home-pages/home-8.html": {
    "status": "ok",
    "checkedAt": "2026-03-11",
    "desktop": "ok",
    "mobile": "ok",
    "note": "gefixed: 11 broken logo li-items (w-[11%] wrappers) vervangen door brand-text items"
  },
  "components/pages/features/layout-629.html": {
    "status": "warn",
    "checkedAt": "2026-03-11",
    "note": "Zelfde als layout-258: oversized Relume-logo placeholder, geen knoppen of echte feature-content."
  },
  "components/pages/hero-headers-new/header-82.html": {
    "status": "ok",
    "checkedAt": "2026-03-11",
    "desktop": "ok",
    "mobile": "ok",
    "note": "gefixed: CDN Tailwind, h1/CTA gestyled, proper padding/centering"
  },
  "components/product-headers/product-header-3.html": {
    "status": "warn",
    "checkedAt": "2026-03-11",
    "note": "Structuur aanwezig (tabs, prijs, Add-to-cart), maar afbeeldingen broken en star-rating als tekst."
  },
  "components/faq/faq-10.html": {
    "status": "warn",
    "checkedAt": "2026-03-11",
    "note": "Twee-koloms layout functioneel, accordions allemaal open (standaard zou er \u00e9\u00e9n open zijn), overflow onderaan."
  },
  "components/blog-headers/blog-27.html": {
    "status": "ok",
    "checkedAt": "2026-03-11",
    "note": "Tagline, heading en filter-knop correct gecentreerd en gestyled. Geen layout-issues."
  },
  "components/application/forms/form-7.html": {
    "status": "ok",
    "checkedAt": "2026-03-11",
    "desktop": "ok",
    "mobile": "ok",
    "note": "gefixed: CDN Tailwind al aanwezig, layout/inputs correct gestyled"
  },
  "components/pages/cta-new/cta-26.html": {
    "status": "ok",
    "checkedAt": "2026-03-11",
    "desktop": "ok",
    "mobile": "ok",
    "note": "fixed: wrapped in article, h1->h2 (cta-new)"
  },
  "components/pages/cta-new/cta-27.html": {
    "status": "ok",
    "checkedAt": "2026-03-11",
    "desktop": "ok",
    "mobile": "ok",
    "note": "fixed: wrapped in article, h1->h2 (cta-new)"
  },
  "components/pages/cta-new/cta-28.html": {
    "status": "ok",
    "checkedAt": "2026-03-11",
    "desktop": "ok",
    "mobile": "ok",
    "note": "fixed: wrapped in article, h1->h2 (cta-new)"
  },
  "components/pages/cta-new/cta-29.html": {
    "status": "ok",
    "checkedAt": "2026-03-11",
    "desktop": "ok",
    "mobile": "ok",
    "note": "fixed: wrapped in article, h1->h2 (cta-new)"
  },
  "components/pages/cta-new/cta-3.html": {
    "status": "ok",
    "checkedAt": "2026-03-11",
    "desktop": "ok",
    "mobile": "ok",
    "note": "fixed: wrapped in article, h1->h2 (cta-new)"
  },
  "components/pages/cta-new/cta-30.html": {
    "status": "ok",
    "checkedAt": "2026-03-11",
    "desktop": "ok",
    "mobile": "ok",
    "note": "fixed: wrapped in article, h1->h2 (cta-new)"
  },
  "components/pages/cta-new/cta-31.html": {
    "status": "ok",
    "checkedAt": "2026-03-11",
    "desktop": "ok",
    "mobile": "ok",
    "note": "fixed: wrapped in article, h1->h2 (cta-new)"
  },
  "components/pages/cta-new/cta-32.html": {
    "status": "ok",
    "checkedAt": "2026-03-11",
    "desktop": "ok",
    "mobile": "ok",
    "note": "fixed: wrapped in article, h1->h2 (cta-new)"
  },
  "components/pages/cta-new/cta-33.html": {
    "status": "ok",
    "checkedAt": "2026-03-11",
    "desktop": "ok",
    "mobile": "ok",
    "note": "fixed: wrapped in article, h1->h2 (cta-new)"
  },
  "components/pages/cta-new/cta-34.html": {
    "status": "ok",
    "checkedAt": "2026-03-11",
    "desktop": "ok",
    "mobile": "ok",
    "note": "fixed: wrapped in article, h1->h2 (cta-new)"
  },
  "components/pages/cta-new/cta-35.html": {
    "status": "ok",
    "checkedAt": "2026-03-11",
    "desktop": "ok",
    "mobile": "ok",
    "note": "fixed: wrapped in article, h1->h2 (cta-new)"
  },
  "components/pages/cta-new/cta-36.html": {
    "status": "ok",
    "checkedAt": "2026-03-11",
    "desktop": "ok",
    "mobile": "ok",
    "note": "fixed: wrapped in article, h1->h2 (cta-new)"
  },
  "components/pages/cta-new/cta-37.html": {
    "status": "ok",
    "checkedAt": "2026-03-11",
    "desktop": "ok",
    "mobile": "ok",
    "note": "fixed: wrapped in article, h1->h2 (cta-new)"
  },
  "components/pages/cta-new/cta-38.html": {
    "status": "ok",
    "checkedAt": "2026-03-11",
    "desktop": "ok",
    "mobile": "ok",
    "note": "fixed: wrapped in article, h1->h2 (cta-new)"
  },
  "components/pages/cta-new/cta-39.html": {
    "status": "ok",
    "checkedAt": "2026-03-11",
    "desktop": "ok",
    "mobile": "ok",
    "note": "fixed: wrapped in article, h1->h2 (cta-new)"
  },
  "components/pages/cta-new/cta-4.html": {
    "status": "ok",
    "checkedAt": "2026-03-11",
    "desktop": "ok",
    "mobile": "ok",
    "note": "fixed: wrapped in article, h1->h2 (cta-new)"
  },
  "components/pages/cta-new/cta-40.html": {
    "status": "ok",
    "checkedAt": "2026-03-11",
    "desktop": "ok",
    "mobile": "ok",
    "note": "fixed: wrapped in article, h1->h2 (cta-new)"
  },
  "components/pages/cta-new/cta-41.html": {
    "status": "ok",
    "checkedAt": "2026-03-11",
    "desktop": "ok",
    "mobile": "ok",
    "note": "fixed: wrapped in article, h1->h2 (cta-new)"
  },
  "components/pages/cta-new/cta-42.html": {
    "status": "ok",
    "checkedAt": "2026-03-11",
    "desktop": "ok",
    "mobile": "ok",
    "note": "fixed: wrapped in article, h1->h2 (cta-new)"
  },
  "components/pages/cta-new/cta-43.html": {
    "status": "ok",
    "checkedAt": "2026-03-11",
    "desktop": "ok",
    "mobile": "ok",
    "note": "fixed: wrapped in article, h1->h2 (cta-new)"
  },
  "components/pages/cta-new/cta-44.html": {
    "status": "ok",
    "checkedAt": "2026-03-11",
    "desktop": "ok",
    "mobile": "ok",
    "note": "fixed: wrapped in article, h1->h2 (cta-new)"
  },
  "components/pages/cta-new/cta-45.html": {
    "status": "ok",
    "checkedAt": "2026-03-11",
    "desktop": "ok",
    "mobile": "ok",
    "note": "fixed: wrapped in article, h1->h2 (cta-new)"
  },
  "components/pages/cta-new/cta-46.html": {
    "status": "ok",
    "checkedAt": "2026-03-11",
    "desktop": "ok",
    "mobile": "ok",
    "note": "fixed: wrapped in article, h1->h2 (cta-new)"
  },
  "components/pages/cta-new/cta-47.html": {
    "status": "ok",
    "checkedAt": "2026-03-11",
    "desktop": "ok",
    "mobile": "ok",
    "note": "fixed: wrapped in article, h1->h2 (cta-new)"
  },
  "components/pages/cta-new/cta-48.html": {
    "status": "ok",
    "checkedAt": "2026-03-11",
    "desktop": "ok",
    "mobile": "ok",
    "note": "fixed: wrapped in article, h1->h2 (cta-new)"
  },
  "components/pages/cta-new/cta-49.html": {
    "status": "ok",
    "checkedAt": "2026-03-11",
    "desktop": "ok",
    "mobile": "ok",
    "note": "fixed: wrapped in article, h1->h2 (cta-new)"
  },
  "components/pages/cta-new/cta-5.html": {
    "status": "ok",
    "checkedAt": "2026-03-11",
    "desktop": "ok",
    "mobile": "ok",
    "note": "fixed: wrapped in article, h1->h2 (cta-new)"
  },
  "components/pages/cta-new/cta-50.html": {
    "status": "ok",
    "checkedAt": "2026-03-11",
    "desktop": "ok",
    "mobile": "ok",
    "note": "fixed: wrapped in article, h1->h2 (cta-new)"
  },
  "components/pages/cta-new/cta-51.html": {
    "status": "ok",
    "checkedAt": "2026-03-11",
    "desktop": "ok",
    "mobile": "ok",
    "note": "fixed: wrapped in article, h1->h2 (cta-new)"
  },
  "components/pages/cta-new/cta-52.html": {
    "status": "ok",
    "checkedAt": "2026-03-11",
    "desktop": "ok",
    "mobile": "ok",
    "note": "fixed: wrapped in article, h1->h2 (cta-new)"
  },
  "components/pages/cta-new/cta-53.html": {
    "status": "ok",
    "checkedAt": "2026-03-11",
    "desktop": "ok",
    "mobile": "ok",
    "note": "fixed: wrapped in article, h1->h2 (cta-new)"
  },
  "components/pages/cta-new/cta-54.html": {
    "status": "ok",
    "checkedAt": "2026-03-11",
    "desktop": "ok",
    "mobile": "ok",
    "note": "fixed: wrapped in article, h1->h2 (cta-new)"
  },
  "components/pages/cta-new/cta-55.html": {
    "status": "ok",
    "checkedAt": "2026-03-11",
    "desktop": "ok",
    "mobile": "ok",
    "note": "fixed: wrapped in article, h1->h2 (cta-new)"
  },
  "components/pages/cta-new/cta-56.html": {
    "status": "ok",
    "checkedAt": "2026-03-11",
    "desktop": "ok",
    "mobile": "ok",
    "note": "fixed: wrapped in article, h1->h2 (cta-new)"
  },
  "components/pages/cta-new/cta-57.html": {
    "status": "ok",
    "checkedAt": "2026-03-11",
    "desktop": "ok",
    "mobile": "ok",
    "note": "fixed: wrapped in article, h1->h2 (cta-new)"
  },
  "components/pages/cta-new/cta-58.html": {
    "status": "ok",
    "checkedAt": "2026-03-11",
    "desktop": "ok",
    "mobile": "ok",
    "note": "fixed: wrapped in article, h1->h2 (cta-new)"
  },
  "components/pages/cta-new/cta-59.html": {
    "status": "ok",
    "checkedAt": "2026-03-11",
    "desktop": "ok",
    "mobile": "ok",
    "note": "fixed: wrapped in article, h1->h2 (cta-new)"
  },
  "components/pages/cta-new/cta-6.html": {
    "status": "ok",
    "checkedAt": "2026-03-11",
    "desktop": "ok",
    "mobile": "ok",
    "note": "fixed: wrapped in article, h1->h2 (cta-new)"
  },
  "components/pages/cta-new/cta-60.html": {
    "status": "ok",
    "checkedAt": "2026-03-11",
    "desktop": "ok",
    "mobile": "ok",
    "note": "fixed: wrapped in article, h1->h2 (cta-new)"
  },
  "components/pages/cta-new/cta-61.html": {
    "status": "ok",
    "checkedAt": "2026-03-11",
    "desktop": "ok",
    "mobile": "ok",
    "note": "fixed: wrapped in article, h1->h2 (cta-new)"
  },
  "components/pages/cta-new/cta-62.html": {
    "status": "ok",
    "checkedAt": "2026-03-11",
    "desktop": "ok",
    "mobile": "ok",
    "note": "fixed: wrapped in article, h1->h2 (cta-new)"
  },
  "components/pages/cta-new/cta-63.html": {
    "status": "ok",
    "checkedAt": "2026-03-11",
    "desktop": "ok",
    "mobile": "ok",
    "note": "fixed: wrapped in article, h1->h2 (cta-new)"
  },
  "components/pages/cta-new/cta-64.html": {
    "status": "ok",
    "checkedAt": "2026-03-11",
    "desktop": "ok",
    "mobile": "ok",
    "note": "fixed: wrapped in article, h1->h2 (cta-new)"
  },
  "components/pages/cta-new/cta-65.html": {
    "status": "ok",
    "checkedAt": "2026-03-11",
    "desktop": "ok",
    "mobile": "ok",
    "note": "fixed: wrapped in article, h1->h2 (cta-new)"
  },
  "components/pages/cta-new/cta-66.html": {
    "status": "ok",
    "checkedAt": "2026-03-11",
    "desktop": "ok",
    "mobile": "ok",
    "note": "fixed: wrapped in article, h1->h2 (cta-new)"
  },
  "components/pages/cta-new/cta-67.html": {
    "status": "ok",
    "checkedAt": "2026-03-11",
    "desktop": "ok",
    "mobile": "ok",
    "note": "fixed: wrapped in article, h1->h2 (cta-new)"
  },
  "components/pages/cta-new/cta-7.html": {
    "status": "ok",
    "checkedAt": "2026-03-11",
    "desktop": "ok",
    "mobile": "ok",
    "note": "fixed: wrapped in article, h1->h2 (cta-new)"
  },
  "components/pages/cta-new/cta-8.html": {
    "status": "ok",
    "checkedAt": "2026-03-11",
    "desktop": "ok",
    "mobile": "ok",
    "note": "fixed: wrapped in article, h1->h2 (cta-new)"
  },
  "components/pages/cta-new/cta-9.html": {
    "status": "ok",
    "checkedAt": "2026-03-11",
    "desktop": "ok",
    "mobile": "ok",
    "note": "fixed: wrapped in article, h1->h2 (cta-new)"
  },
  "components/pages/event-headers/event-header-1.html": {
    "status": "ok",
    "checkedAt": "2026-03-11",
    "desktop": "ok",
    "mobile": "ok",
    "note": "fixed: wrapped in article"
  },
  "components/pages/event-headers/event-header-2.html": {
    "status": "ok",
    "checkedAt": "2026-03-11",
    "desktop": "ok",
    "mobile": "ok",
    "note": "fixed: wrapped in article"
  },
  "components/pages/event-headers/event-header-3.html": {
    "status": "ok",
    "checkedAt": "2026-03-11",
    "desktop": "ok",
    "mobile": "ok",
    "note": "fixed: wrapped in article"
  },
  "components/pages/event-headers/event-header-4.html": {
    "status": "ok",
    "checkedAt": "2026-03-11",
    "desktop": "ok",
    "mobile": "ok",
    "note": "fixed: wrapped in article"
  },
  "components/pages/event-headers/event-header-5.html": {
    "status": "ok",
    "checkedAt": "2026-03-11",
    "desktop": "ok",
    "mobile": "ok",
    "note": "fixed: wrapped in article"
  },
  "components/pages/event-headers/event-header-6.html": {
    "status": "ok",
    "checkedAt": "2026-03-11",
    "desktop": "ok",
    "mobile": "ok",
    "note": "fixed: wrapped in article"
  },
  "components/pages/event-item-headers/event-item-header-1.html": {
    "status": "ok",
    "checkedAt": "2026-03-11",
    "desktop": "ok",
    "mobile": "ok",
    "note": "fixed: wrapped in article"
  },
  "components/pages/event-item-headers/event-item-header-10.html": {
    "status": "ok",
    "checkedAt": "2026-03-11",
    "desktop": "ok",
    "mobile": "ok",
    "note": "fixed: wrapped in article"
  },
  "components/pages/event-item-headers/event-item-header-11.html": {
    "status": "ok",
    "checkedAt": "2026-03-11",
    "desktop": "ok",
    "mobile": "ok",
    "note": "fixed: wrapped in article"
  },
  "components/pages/event-item-headers/event-item-header-2.html": {
    "status": "ok",
    "checkedAt": "2026-03-11",
    "desktop": "ok",
    "mobile": "ok",
    "note": "fixed: wrapped in article"
  },
  "components/pages/event-item-headers/event-item-header-3.html": {
    "status": "ok",
    "checkedAt": "2026-03-11",
    "desktop": "ok",
    "mobile": "ok",
    "note": "fixed: wrapped in article"
  },
  "components/pages/event-item-headers/event-item-header-4.html": {
    "status": "ok",
    "checkedAt": "2026-03-11",
    "desktop": "ok",
    "mobile": "ok",
    "note": "fixed: wrapped in article"
  },
  "components/pages/event-item-headers/event-item-header-5.html": {
    "status": "ok",
    "checkedAt": "2026-03-11",
    "desktop": "ok",
    "mobile": "ok",
    "note": "fixed: wrapped in article"
  },
  "components/pages/event-item-headers/event-item-header-6.html": {
    "status": "ok",
    "checkedAt": "2026-03-11",
    "desktop": "ok",
    "mobile": "ok",
    "note": "fixed: wrapped in article"
  },
  "components/pages/event-item-headers/event-item-header-7.html": {
    "status": "ok",
    "checkedAt": "2026-03-11",
    "desktop": "ok",
    "mobile": "ok",
    "note": "fixed: wrapped in article"
  },
  "components/pages/event-item-headers/event-item-header-8.html": {
    "status": "ok",
    "checkedAt": "2026-03-11",
    "desktop": "ok",
    "mobile": "ok",
    "note": "fixed: wrapped in article"
  },
  "components/pages/event-item-headers/event-item-header-9.html": {
    "status": "ok",
    "checkedAt": "2026-03-11",
    "desktop": "ok",
    "mobile": "ok",
    "note": "fixed: wrapped in article"
  },
  "components/pages/event-sections/event-1.html": {
    "status": "ok",
    "checkedAt": "2026-03-11",
    "desktop": "ok",
    "mobile": "ok",
    "note": "fixed: wrapped in article"
  },
  "components/pages/event-sections/event-10.html": {
    "status": "ok",
    "checkedAt": "2026-03-11",
    "desktop": "ok",
    "mobile": "ok",
    "note": "fixed: wrapped in article"
  },
  "components/pages/event-sections/event-11.html": {
    "status": "ok",
    "checkedAt": "2026-03-11",
    "desktop": "ok",
    "mobile": "ok",
    "note": "fixed: wrapped in article"
  },
  "components/pages/event-sections/event-12.html": {
    "status": "ok",
    "checkedAt": "2026-03-11",
    "desktop": "ok",
    "mobile": "ok",
    "note": "fixed: wrapped in article"
  },
  "components/pages/event-sections/event-13.html": {
    "status": "ok",
    "checkedAt": "2026-03-11",
    "desktop": "ok",
    "mobile": "ok",
    "note": "fixed: wrapped in article"
  },
  "components/pages/event-sections/event-14.html": {
    "status": "ok",
    "checkedAt": "2026-03-11",
    "desktop": "ok",
    "mobile": "ok",
    "note": "fixed: wrapped in article"
  },
  "components/pages/event-sections/event-15.html": {
    "status": "ok",
    "checkedAt": "2026-03-11",
    "desktop": "ok",
    "mobile": "ok",
    "note": "fixed: wrapped in article"
  },
  "components/pages/event-sections/event-16.html": {
    "status": "ok",
    "checkedAt": "2026-03-11",
    "desktop": "ok",
    "mobile": "ok",
    "note": "fixed: wrapped in article"
  },
  "components/pages/event-sections/event-17.html": {
    "status": "ok",
    "checkedAt": "2026-03-11",
    "desktop": "ok",
    "mobile": "ok",
    "note": "fixed: wrapped in article"
  },
  "components/pages/event-sections/event-18.html": {
    "status": "ok",
    "checkedAt": "2026-03-11",
    "desktop": "ok",
    "mobile": "ok",
    "note": "fixed: wrapped in article"
  },
  "components/pages/event-sections/event-19.html": {
    "status": "ok",
    "checkedAt": "2026-03-11",
    "desktop": "ok",
    "mobile": "ok",
    "note": "fixed: wrapped in article"
  },
  "components/pages/event-sections/event-2.html": {
    "status": "ok",
    "checkedAt": "2026-03-11",
    "desktop": "ok",
    "mobile": "ok",
    "note": "fixed: wrapped in article"
  },
  "components/pages/event-sections/event-20.html": {
    "status": "ok",
    "checkedAt": "2026-03-11",
    "desktop": "ok",
    "mobile": "ok",
    "note": "fixed: wrapped in article"
  },
  "components/pages/event-sections/event-21.html": {
    "status": "ok",
    "checkedAt": "2026-03-11",
    "desktop": "ok",
    "mobile": "ok",
    "note": "fixed: wrapped in article"
  },
  "components/pages/event-sections/event-22.html": {
    "status": "ok",
    "checkedAt": "2026-03-11",
    "desktop": "ok",
    "mobile": "ok",
    "note": "fixed: wrapped in article"
  },
  "components/pages/event-sections/event-23.html": {
    "status": "ok",
    "checkedAt": "2026-03-11",
    "desktop": "ok",
    "mobile": "ok",
    "note": "fixed: wrapped in article"
  },
  "components/pages/event-sections/event-24.html": {
    "status": "ok",
    "checkedAt": "2026-03-11",
    "desktop": "ok",
    "mobile": "ok",
    "note": "fixed: wrapped in article"
  },
  "components/pages/event-sections/event-25.html": {
    "status": "ok",
    "checkedAt": "2026-03-11",
    "desktop": "ok",
    "mobile": "ok",
    "note": "fixed: wrapped in article"
  },
  "components/pages/event-sections/event-26.html": {
    "status": "ok",
    "checkedAt": "2026-03-11",
    "desktop": "ok",
    "mobile": "ok",
    "note": "fixed: wrapped in article"
  },
  "components/pages/event-sections/event-27.html": {
    "status": "ok",
    "checkedAt": "2026-03-11",
    "desktop": "ok",
    "mobile": "ok",
    "note": "fixed: wrapped in article"
  },
  "components/pages/event-sections/event-28.html": {
    "status": "ok",
    "checkedAt": "2026-03-11",
    "desktop": "ok",
    "mobile": "ok",
    "note": "fixed: wrapped in article"
  },
  "components/pages/event-sections/event-29.html": {
    "status": "ok",
    "checkedAt": "2026-03-11",
    "desktop": "ok",
    "mobile": "ok",
    "note": "fixed: wrapped in article"
  },
  "components/pages/event-sections/event-3.html": {
    "status": "ok",
    "checkedAt": "2026-03-11",
    "desktop": "ok",
    "mobile": "ok",
    "note": "fixed: wrapped in article"
  },
  "components/pages/event-sections/event-30.html": {
    "status": "ok",
    "checkedAt": "2026-03-11",
    "desktop": "ok",
    "mobile": "ok",
    "note": "fixed: wrapped in article"
  },
  "components/pages/event-sections/event-31.html": {
    "status": "ok",
    "checkedAt": "2026-03-11",
    "desktop": "ok",
    "mobile": "ok",
    "note": "fixed: wrapped in article"
  },
  "components/pages/event-sections/event-32.html": {
    "status": "ok",
    "checkedAt": "2026-03-11",
    "desktop": "ok",
    "mobile": "ok",
    "note": "fixed: wrapped in article"
  },
  "components/pages/event-sections/event-33.html": {
    "status": "ok",
    "checkedAt": "2026-03-11",
    "desktop": "ok",
    "mobile": "ok",
    "note": "fixed: wrapped in article"
  },
  "components/pages/event-sections/event-34.html": {
    "status": "ok",
    "checkedAt": "2026-03-11",
    "desktop": "ok",
    "mobile": "ok",
    "note": "fixed: wrapped in article"
  },
  "components/pages/event-sections/event-35.html": {
    "status": "ok",
    "checkedAt": "2026-03-11",
    "desktop": "ok",
    "mobile": "ok",
    "note": "fixed: wrapped in article"
  },
  "components/pages/event-sections/event-36.html": {
    "status": "ok",
    "checkedAt": "2026-03-11",
    "desktop": "ok",
    "mobile": "ok",
    "note": "fixed: wrapped in article"
  },
  "components/pages/event-sections/event-37.html": {
    "status": "ok",
    "checkedAt": "2026-03-11",
    "desktop": "ok",
    "mobile": "ok",
    "note": "fixed: wrapped in article"
  },
  "components/pages/event-sections/event-4.html": {
    "status": "ok",
    "checkedAt": "2026-03-11",
    "desktop": "ok",
    "mobile": "ok",
    "note": "fixed: wrapped in article"
  },
  "components/pages/event-sections/event-5.html": {
    "status": "ok",
    "checkedAt": "2026-03-11",
    "desktop": "ok",
    "mobile": "ok",
    "note": "fixed: wrapped in article"
  },
  "components/pages/event-sections/event-6.html": {
    "status": "ok",
    "checkedAt": "2026-03-11",
    "desktop": "ok",
    "mobile": "ok",
    "note": "fixed: wrapped in article"
  },
  "components/pages/event-sections/event-7.html": {
    "status": "ok",
    "checkedAt": "2026-03-11",
    "desktop": "ok",
    "mobile": "ok",
    "note": "gefixed: <div>\u2192<article>, container mx-auto px-6\u2192max-w-screen-xl; screenshot ok"
  },
  "components/pages/event-sections/event-8.html": {
    "status": "ok",
    "checkedAt": "2026-03-11",
    "desktop": "ok",
    "mobile": "ok",
    "note": "gefixed: <div>\u2192<article>, container mx-auto px-6\u2192max-w-screen-xl"
  },
  "components/pages/event-sections/event-9.html": {
    "status": "ok",
    "checkedAt": "2026-03-11",
    "desktop": "ok",
    "mobile": "ok",
    "note": "gefixed: <div>\u2192<article>, container mx-auto px-6\u2192max-w-screen-xl"
  },
  "components/pages/faq/faq-1.html": {
    "status": "ok",
    "checkedAt": "2026-03-11",
    "desktop": "ok",
    "mobile": "ok",
    "note": "gefixed: <div>\u2192<article>, container mx-auto px-6\u2192max-w-screen-xl"
  },
  "components/pages/faq/faq-10.html": {
    "status": "ok",
    "checkedAt": "2026-03-11",
    "desktop": "ok",
    "mobile": "ok",
    "note": "gefixed: <div>\u2192<article>, container mx-auto px-6\u2192max-w-screen-xl; screenshot ok"
  },
  "components/pages/faq/faq-11.html": {
    "status": "ok",
    "checkedAt": "2026-03-11",
    "desktop": "ok",
    "mobile": "ok",
    "note": "gefixed: <div>\u2192<article>, container mx-auto px-6\u2192max-w-screen-xl"
  },
  "components/pages/faq/faq-12.html": {
    "status": "ok",
    "checkedAt": "2026-03-11",
    "desktop": "ok",
    "mobile": "ok",
    "note": "gefixed: <div>\u2192<article>, container mx-auto px-6\u2192max-w-screen-xl"
  },
  "components/pages/faq/faq-13.html": {
    "status": "ok",
    "checkedAt": "2026-03-11",
    "desktop": "ok",
    "mobile": "ok",
    "note": "gefixed: <div>\u2192<article>, container mx-auto px-6\u2192max-w-screen-xl"
  },
  "components/pages/faq/faq-14.html": {
    "status": "ok",
    "checkedAt": "2026-03-11",
    "desktop": "ok",
    "mobile": "ok",
    "note": "gefixed: <div>\u2192<article>, container mx-auto px-6\u2192max-w-screen-xl"
  },
  "components/pages/faq/faq-2.html": {
    "status": "ok",
    "checkedAt": "2026-03-11",
    "desktop": "ok",
    "mobile": "ok",
    "note": "gefixed: <div>\u2192<article>, container mx-auto px-6\u2192max-w-screen-xl"
  },
  "components/pages/faq/faq-3.html": {
    "status": "ok",
    "checkedAt": "2026-03-11",
    "desktop": "ok",
    "mobile": "ok",
    "note": "gefixed: <div>\u2192<article>, container mx-auto px-6\u2192max-w-screen-xl"
  },
  "components/pages/faq/faq-4.html": {
    "status": "ok",
    "checkedAt": "2026-03-11",
    "desktop": "ok",
    "mobile": "ok",
    "note": "gefixed: <div>\u2192<article>, container mx-auto px-6\u2192max-w-screen-xl"
  },
  "components/pages/faq/faq-5.html": {
    "status": "ok",
    "checkedAt": "2026-03-11",
    "desktop": "ok",
    "mobile": "ok",
    "note": "gefixed: <div>\u2192<article>, container mx-auto px-6\u2192max-w-screen-xl; screenshot ok"
  },
  "components/pages/faq/faq-6.html": {
    "status": "ok",
    "checkedAt": "2026-03-11",
    "desktop": "ok",
    "mobile": "ok",
    "note": "gefixed: <div>\u2192<article>, container mx-auto px-6\u2192max-w-screen-xl"
  },
  "components/pages/faq/faq-7.html": {
    "status": "ok",
    "checkedAt": "2026-03-11",
    "desktop": "ok",
    "mobile": "ok",
    "note": "gefixed: <div>\u2192<article>, container mx-auto px-6\u2192max-w-screen-xl"
  },
  "components/pages/faq/faq-8.html": {
    "status": "ok",
    "checkedAt": "2026-03-11",
    "desktop": "ok",
    "mobile": "ok",
    "note": "gefixed: <div>\u2192<article>, container mx-auto px-6\u2192max-w-screen-xl"
  },
  "components/pages/faq/faq-9.html": {
    "status": "ok",
    "checkedAt": "2026-03-11",
    "desktop": "ok",
    "mobile": "ok",
    "note": "gefixed: <div>\u2192<article>, container mx-auto px-6\u2192max-w-screen-xl"
  },
  "components/pages/features/layout-1.html": {
    "status": "ok",
    "checkedAt": "2026-03-11",
    "desktop": "ok",
    "mobile": "ok",
    "note": "gefixed: <div>\u2192<article>, container mx-auto px-6\u2192max-w-screen-xl"
  },
  "components/pages/features/layout-10.html": {
    "status": "ok",
    "checkedAt": "2026-03-11",
    "desktop": "ok",
    "mobile": "ok",
    "note": "gefixed: <div>\u2192<article>, container mx-auto px-6\u2192max-w-screen-xl"
  },
  "components/pages/features/layout-100.html": {
    "status": "ok",
    "checkedAt": "2026-03-11",
    "desktop": "ok",
    "mobile": "ok",
    "note": "gefixed: <div>\u2192<article>, container mx-auto px-6\u2192max-w-screen-xl"
  },
  "components/pages/features/layout-101.html": {
    "status": "ok",
    "checkedAt": "2026-03-11",
    "desktop": "ok",
    "mobile": "ok",
    "note": "gefixed: <div>\u2192<article>, container mx-auto px-6\u2192max-w-screen-xl"
  },
  "components/pages/features/layout-102.html": {
    "status": "ok",
    "checkedAt": "2026-03-11",
    "desktop": "ok",
    "mobile": "ok",
    "note": "gefixed: <div>\u2192<article>, container mx-auto px-6\u2192max-w-screen-xl"
  },
  "components/pages/features/layout-103.html": {
    "status": "ok",
    "checkedAt": "2026-03-11",
    "desktop": "ok",
    "mobile": "ok",
    "note": "gefixed: <div>\u2192<article>, container mx-auto px-6\u2192max-w-screen-xl"
  },
  "components/pages/features/layout-104.html": {
    "status": "ok",
    "checkedAt": "2026-03-11",
    "desktop": "ok",
    "mobile": "ok",
    "note": "gefixed: <div>\u2192<article>, container mx-auto px-6\u2192max-w-screen-xl"
  },
  "components/pages/features/layout-105.html": {
    "status": "ok",
    "checkedAt": "2026-03-11",
    "desktop": "ok",
    "mobile": "ok",
    "note": "gefixed: <div>\u2192<article>, container mx-auto px-6\u2192max-w-screen-xl"
  },
  "components/pages/features/layout-106.html": {
    "status": "ok",
    "checkedAt": "2026-03-11",
    "desktop": "ok",
    "mobile": "ok",
    "note": "gefixed: <div>\u2192<article>, container mx-auto px-6\u2192max-w-screen-xl"
  },
  "components/pages/features/layout-107.html": {
    "status": "ok",
    "checkedAt": "2026-03-11",
    "desktop": "ok",
    "mobile": "ok",
    "note": "gefixed: <div>\u2192<article>, container mx-auto px-6\u2192max-w-screen-xl"
  },
  "components/pages/features/layout-108.html": {
    "status": "ok",
    "checkedAt": "2026-03-11",
    "desktop": "ok",
    "mobile": "ok",
    "note": "gefixed: <div>\u2192<article>, container mx-auto px-6\u2192max-w-screen-xl"
  },
  "components/pages/features/layout-109.html": {
    "status": "ok",
    "checkedAt": "2026-03-11",
    "desktop": "ok",
    "mobile": "ok",
    "note": "gefixed: <div>\u2192<article>, container mx-auto px-6\u2192max-w-screen-xl"
  },
  "components/pages/features/layout-11.html": {
    "status": "ok",
    "checkedAt": "2026-03-11",
    "desktop": "ok",
    "mobile": "ok",
    "note": "gefixed: <div>\u2192<article>, container mx-auto px-6\u2192max-w-screen-xl"
  },
  "components/pages/features/layout-110.html": {
    "status": "ok",
    "checkedAt": "2026-03-11",
    "desktop": "ok",
    "mobile": "ok",
    "note": "gefixed: <div>\u2192<article>, container mx-auto px-6\u2192max-w-screen-xl"
  },
  "components/pages/features/layout-111.html": {
    "status": "ok",
    "checkedAt": "2026-03-11",
    "desktop": "ok",
    "mobile": "ok",
    "note": "gefixed: <div>\u2192<article>, container mx-auto px-6\u2192max-w-screen-xl"
  },
  "components/pages/features/layout-112.html": {
    "status": "ok",
    "checkedAt": "2026-03-11",
    "desktop": "ok",
    "mobile": "ok",
    "note": "gefixed: <div>\u2192<article>, container mx-auto px-6\u2192max-w-screen-xl"
  },
  "components/pages/features/layout-113.html": {
    "status": "ok",
    "checkedAt": "2026-03-11",
    "desktop": "ok",
    "mobile": "ok",
    "note": "gefixed: <div>\u2192<article>, container mx-auto px-6\u2192max-w-screen-xl"
  },
  "components/pages/features/layout-114.html": {
    "status": "ok",
    "checkedAt": "2026-03-11",
    "desktop": "ok",
    "mobile": "ok",
    "note": "gefixed: <div>\u2192<article>, container mx-auto px-6\u2192max-w-screen-xl"
  },
  "components/pages/features/layout-115.html": {
    "status": "ok",
    "checkedAt": "2026-03-11",
    "desktop": "ok",
    "mobile": "ok",
    "note": "gefixed: <div>\u2192<article>, container mx-auto px-6\u2192max-w-screen-xl"
  },
  "components/pages/features/layout-116.html": {
    "status": "ok",
    "checkedAt": "2026-03-11",
    "desktop": "ok",
    "mobile": "ok",
    "note": "gefixed: <div>\u2192<article>, container mx-auto px-6\u2192max-w-screen-xl"
  },
  "components/pages/features/layout-117.html": {
    "status": "ok",
    "checkedAt": "2026-03-11",
    "desktop": "ok",
    "mobile": "ok",
    "note": "gefixed: <div>\u2192<article>, container mx-auto px-6\u2192max-w-screen-xl"
  },
  "components/pages/features/layout-118.html": {
    "status": "ok",
    "checkedAt": "2026-03-11",
    "desktop": "ok",
    "mobile": "ok",
    "note": "gefixed: <div>\u2192<article>, container mx-auto px-6\u2192max-w-screen-xl"
  },
  "components/pages/features/layout-119.html": {
    "status": "ok",
    "checkedAt": "2026-03-11",
    "desktop": "ok",
    "mobile": "ok",
    "note": "gefixed: <div>\u2192<article>, container mx-auto px-6\u2192max-w-screen-xl"
  },
  "components/pages/features/layout-12.html": {
    "status": "ok",
    "checkedAt": "2026-03-11",
    "desktop": "ok",
    "mobile": "ok",
    "note": "gefixed: <div>\u2192<article>, container mx-auto px-6\u2192max-w-screen-xl"
  },
  "components/pages/features/layout-120.html": {
    "status": "ok",
    "checkedAt": "2026-03-11",
    "desktop": "ok",
    "mobile": "ok",
    "note": "gefixed: <div>\u2192<article>, container mx-auto px-6\u2192max-w-screen-xl"
  },
  "components/pages/features/layout-121.html": {
    "status": "ok",
    "checkedAt": "2026-03-11",
    "desktop": "ok",
    "mobile": "ok",
    "note": "gefixed: <div>\u2192<article>, container mx-auto px-6\u2192max-w-screen-xl"
  },
  "components/pages/features/layout-122.html": {
    "status": "ok",
    "checkedAt": "2026-03-11",
    "desktop": "ok",
    "mobile": "ok",
    "note": "gefixed: <div>\u2192<article>, container mx-auto px-6\u2192max-w-screen-xl"
  },
  "components/pages/features/layout-123.html": {
    "status": "ok",
    "checkedAt": "2026-03-11",
    "desktop": "ok",
    "mobile": "ok",
    "note": "gefixed: <div>\u2192<article>, container mx-auto px-6\u2192max-w-screen-xl"
  },
  "components/pages/features/layout-124.html": {
    "status": "ok",
    "checkedAt": "2026-03-11",
    "desktop": "ok",
    "mobile": "ok",
    "note": "gefixed: <div>\u2192<article>, container mx-auto px-6\u2192max-w-screen-xl"
  },
  "components/pages/features/layout-125.html": {
    "status": "ok",
    "checkedAt": "2026-03-11",
    "desktop": "ok",
    "mobile": "ok",
    "note": "gefixed: <div>\u2192<article>, container mx-auto px-6\u2192max-w-screen-xl; screenshot ok"
  },
  "components/pages/features/layout-126.html": {
    "status": "ok",
    "checkedAt": "2026-03-11",
    "desktop": "ok",
    "mobile": "ok",
    "note": "gefixed: <div>\u2192<article>, container mx-auto px-6\u2192max-w-screen-xl"
  },
  "components/pages/features/layout-127.html": {
    "status": "ok",
    "checkedAt": "2026-03-11",
    "desktop": "ok",
    "mobile": "ok",
    "note": "gefixed: <div>\u2192<article>, container mx-auto px-6\u2192max-w-screen-xl"
  },
  "components/pages/features/layout-128.html": {
    "status": "ok",
    "checkedAt": "2026-03-11",
    "desktop": "ok",
    "mobile": "ok",
    "note": "gefixed: <div>\u2192<article>, container mx-auto px-6\u2192max-w-screen-xl"
  },
  "components/pages/features/layout-129.html": {
    "status": "ok",
    "checkedAt": "2026-03-11",
    "desktop": "ok",
    "mobile": "ok",
    "note": "gefixed: <div>\u2192<article>, container mx-auto px-6\u2192max-w-screen-xl"
  },
  "components/pages/features/layout-13.html": {
    "status": "ok",
    "checkedAt": "2026-03-11",
    "desktop": "ok",
    "mobile": "ok",
    "note": "gefixed: <div>\u2192<article>, container mx-auto px-6\u2192max-w-screen-xl"
  },
  "components/pages/features/layout-130.html": {
    "status": "ok",
    "checkedAt": "2026-03-11",
    "desktop": "ok",
    "mobile": "ok",
    "note": "gefixed: <div>\u2192<article>, container mx-auto px-6\u2192max-w-screen-xl"
  },
  "components/pages/features/layout-131.html": {
    "status": "ok",
    "checkedAt": "2026-03-11",
    "desktop": "ok",
    "mobile": "ok",
    "note": "gefixed: <div>\u2192<article>, container mx-auto px-6\u2192max-w-screen-xl"
  },
  "components/pages/features/layout-132.html": {
    "status": "ok",
    "checkedAt": "2026-03-11",
    "desktop": "ok",
    "mobile": "ok",
    "note": "gefixed: <div>\u2192<article>, container mx-auto px-6\u2192max-w-screen-xl"
  },
  "components/pages/features/layout-133.html": {
    "status": "ok",
    "checkedAt": "2026-03-11",
    "desktop": "ok",
    "mobile": "ok",
    "note": "gefixed: <div>\u2192<article>, container mx-auto px-6\u2192max-w-screen-xl"
  },
  "components/pages/features/layout-134.html": {
    "status": "ok",
    "checkedAt": "2026-03-11",
    "desktop": "ok",
    "mobile": "ok",
    "note": "gefixed: <div>\u2192<article>, container mx-auto px-6\u2192max-w-screen-xl"
  },
  "components/pages/features/layout-135.html": {
    "status": "ok",
    "checkedAt": "2026-03-11",
    "desktop": "ok",
    "mobile": "ok",
    "note": "gefixed: <div>\u2192<article>, container mx-auto px-6\u2192max-w-screen-xl"
  },
  "components/pages/features/layout-136.html": {
    "status": "ok",
    "checkedAt": "2026-03-11",
    "desktop": "ok",
    "mobile": "ok",
    "note": "gefixed: <div>\u2192<article>, container mx-auto px-6\u2192max-w-screen-xl"
  },
  "components/pages/features/layout-137.html": {
    "status": "ok",
    "checkedAt": "2026-03-11",
    "desktop": "ok",
    "mobile": "ok",
    "note": "gefixed: <div>\u2192<article>, container mx-auto px-6\u2192max-w-screen-xl"
  },
  "components/pages/features/layout-138.html": {
    "status": "ok",
    "checkedAt": "2026-03-11",
    "desktop": "ok",
    "mobile": "ok",
    "note": "gefixed: <div>\u2192<article>, container mx-auto px-6\u2192max-w-screen-xl"
  },
  "components/pages/features/layout-139.html": {
    "status": "ok",
    "checkedAt": "2026-03-11",
    "desktop": "ok",
    "mobile": "ok",
    "note": "gefixed: <div>\u2192<article>, container mx-auto px-6\u2192max-w-screen-xl"
  },
  "components/pages/features/layout-14.html": {
    "status": "ok",
    "checkedAt": "2026-03-11",
    "desktop": "ok",
    "mobile": "ok",
    "note": "gefixed: <div>\u2192<article>, container mx-auto px-6\u2192max-w-screen-xl"
  },
  "components/pages/features/layout-140.html": {
    "status": "ok",
    "checkedAt": "2026-03-11",
    "desktop": "ok",
    "mobile": "ok",
    "note": "gefixed: <div>\u2192<article>, container mx-auto px-6\u2192max-w-screen-xl"
  },
  "components/pages/features/layout-141.html": {
    "status": "ok",
    "checkedAt": "2026-03-11",
    "desktop": "ok",
    "mobile": "ok",
    "note": "gefixed: <div>\u2192<article>, container mx-auto px-6\u2192max-w-screen-xl"
  },
  "components/pages/features/layout-142.html": {
    "status": "ok",
    "checkedAt": "2026-03-11",
    "desktop": "ok",
    "mobile": "ok",
    "note": "gefixed: <div>\u2192<article>, container mx-auto px-6\u2192max-w-screen-xl"
  },
  "components/pages/features/layout-143.html": {
    "status": "ok",
    "checkedAt": "2026-03-11",
    "desktop": "ok",
    "mobile": "ok",
    "note": "gefixed: <div>\u2192<article>, container mx-auto px-6\u2192max-w-screen-xl"
  },
  "components/pages/features/layout-144.html": {
    "status": "ok",
    "checkedAt": "2026-03-11",
    "desktop": "ok",
    "mobile": "ok",
    "note": "gefixed: <div>\u2192<article>, container mx-auto px-6\u2192max-w-screen-xl"
  },
  "components/pages/features/layout-145.html": {
    "status": "ok",
    "checkedAt": "2026-03-11",
    "desktop": "ok",
    "mobile": "ok",
    "note": "gefixed: <div>\u2192<article>, container mx-auto px-6\u2192max-w-screen-xl"
  },
  "components/pages/features/layout-146.html": {
    "status": "ok",
    "checkedAt": "2026-03-11",
    "desktop": "ok",
    "mobile": "ok",
    "note": "gefixed: <div>\u2192<article>, container mx-auto px-6\u2192max-w-screen-xl"
  },
  "components/pages/features/layout-147.html": {
    "status": "ok",
    "checkedAt": "2026-03-11",
    "desktop": "ok",
    "mobile": "ok",
    "note": "gefixed: <div>\u2192<article>, container mx-auto px-6\u2192max-w-screen-xl"
  },
  "components/pages/features/layout-148.html": {
    "status": "ok",
    "checkedAt": "2026-03-11",
    "desktop": "ok",
    "mobile": "ok",
    "note": "gefixed: <div>\u2192<article>, container mx-auto px-6\u2192max-w-screen-xl"
  },
  "components/pages/features/layout-149.html": {
    "status": "ok",
    "checkedAt": "2026-03-11",
    "desktop": "ok",
    "mobile": "ok",
    "note": "gefixed: <div>\u2192<article>, container mx-auto px-6\u2192max-w-screen-xl"
  },
  "components/pages/features/layout-15.html": {
    "status": "ok",
    "checkedAt": "2026-03-11",
    "desktop": "ok",
    "mobile": "ok",
    "note": "gefixed: <div>\u2192<article>, container mx-auto px-6\u2192max-w-screen-xl"
  },
  "components/pages/features/layout-150.html": {
    "status": "ok",
    "checkedAt": "2026-03-11",
    "desktop": "ok",
    "mobile": "ok",
    "note": "gefixed: <div>\u2192<article>, container mx-auto px-6\u2192max-w-screen-xl"
  },
  "components/pages/features/layout-151.html": {
    "status": "ok",
    "checkedAt": "2026-03-11",
    "desktop": "ok",
    "mobile": "ok",
    "note": "gefixed: <div>\u2192<article>, container mx-auto px-6\u2192max-w-screen-xl"
  },
  "components/pages/features/layout-152.html": {
    "status": "ok",
    "checkedAt": "2026-03-11",
    "desktop": "ok",
    "mobile": "ok",
    "note": "gefixed: <div>\u2192<article>, container mx-auto px-6\u2192max-w-screen-xl"
  },
  "components/pages/features/layout-153.html": {
    "status": "ok",
    "checkedAt": "2026-03-11",
    "desktop": "ok",
    "mobile": "ok",
    "note": "gefixed: <div>\u2192<article>, container mx-auto px-6\u2192max-w-screen-xl"
  },
  "components/pages/features/layout-154.html": {
    "status": "ok",
    "checkedAt": "2026-03-11",
    "desktop": "ok",
    "mobile": "ok",
    "note": "gefixed: <div>\u2192<article>, container mx-auto px-6\u2192max-w-screen-xl"
  },
  "components/pages/features/layout-155.html": {
    "status": "ok",
    "checkedAt": "2026-03-11",
    "desktop": "ok",
    "mobile": "ok",
    "note": "gefixed: <div>\u2192<article>, container mx-auto px-6\u2192max-w-screen-xl"
  },
  "components/pages/features/layout-156.html": {
    "status": "ok",
    "checkedAt": "2026-03-11",
    "desktop": "ok",
    "mobile": "ok",
    "note": "gefixed: <div>\u2192<article>, container mx-auto px-6\u2192max-w-screen-xl"
  },
  "components/pages/features/layout-157.html": {
    "status": "ok",
    "checkedAt": "2026-03-11",
    "desktop": "ok",
    "mobile": "ok",
    "note": "gefixed: <div>\u2192<article>, container mx-auto px-6\u2192max-w-screen-xl"
  },
  "components/pages/features/layout-158.html": {
    "status": "ok",
    "checkedAt": "2026-03-11",
    "desktop": "ok",
    "mobile": "ok",
    "note": "gefixed: <div>\u2192<article>, container mx-auto px-6\u2192max-w-screen-xl"
  },
  "components/pages/features/layout-159.html": {
    "status": "ok",
    "checkedAt": "2026-03-11",
    "desktop": "ok",
    "mobile": "ok",
    "note": "gefixed: <div>\u2192<article>, container mx-auto px-6\u2192max-w-screen-xl"
  },
  "components/pages/features/layout-16.html": {
    "status": "ok",
    "checkedAt": "2026-03-11",
    "desktop": "ok",
    "mobile": "ok",
    "note": "gefixed: <div>\u2192<article>, container mx-auto px-6\u2192max-w-screen-xl"
  },
  "components/pages/features/layout-160.html": {
    "status": "ok",
    "checkedAt": "2026-03-11",
    "desktop": "ok",
    "mobile": "ok",
    "note": "gefixed: <div>\u2192<article>, container mx-auto px-6\u2192max-w-screen-xl"
  },
  "components/pages/features/layout-161.html": {
    "status": "ok",
    "checkedAt": "2026-03-11",
    "desktop": "ok",
    "mobile": "ok",
    "note": "gefixed: <div>\u2192<article>, container mx-auto px-6\u2192max-w-screen-xl"
  },
  "components/pages/features/layout-162.html": {
    "status": "ok",
    "checkedAt": "2026-03-11",
    "desktop": "ok",
    "mobile": "ok",
    "note": "gefixed: <div>\u2192<article>, container mx-auto px-6\u2192max-w-screen-xl"
  },
  "components/pages/features/layout-163.html": {
    "status": "ok",
    "checkedAt": "2026-03-11",
    "desktop": "ok",
    "mobile": "ok",
    "note": "gefixed: <div>\u2192<article>, container mx-auto px-6\u2192max-w-screen-xl"
  },
  "components/pages/features/layout-164.html": {
    "status": "ok",
    "checkedAt": "2026-03-11",
    "desktop": "ok",
    "mobile": "ok",
    "note": "gefixed: <div>\u2192<article>, container mx-auto px-6\u2192max-w-screen-xl"
  },
  "components/pages/features/layout-165.html": {
    "status": "ok",
    "checkedAt": "2026-03-11",
    "desktop": "ok",
    "mobile": "ok",
    "note": "gefixed: <div>\u2192<article>, container mx-auto px-6\u2192max-w-screen-xl"
  },
  "components/pages/features/layout-166.html": {
    "status": "ok",
    "checkedAt": "2026-03-11",
    "desktop": "ok",
    "mobile": "ok",
    "note": "gefixed: <div>\u2192<article>, container mx-auto px-6\u2192max-w-screen-xl"
  },
  "components/pages/features/layout-167.html": {
    "status": "ok",
    "checkedAt": "2026-03-11",
    "desktop": "ok",
    "mobile": "ok",
    "note": "gefixed: <div>\u2192<article>, container mx-auto px-6\u2192max-w-screen-xl"
  },
  "components/pages/features/layout-168.html": {
    "status": "ok",
    "checkedAt": "2026-03-11",
    "desktop": "ok",
    "mobile": "ok",
    "note": "gefixed: <div>\u2192<article>, container mx-auto px-6\u2192max-w-screen-xl"
  },
  "components/pages/features/layout-169.html": {
    "status": "ok",
    "checkedAt": "2026-03-11",
    "desktop": "ok",
    "mobile": "ok",
    "note": "gefixed: <div>\u2192<article>, container mx-auto px-6\u2192max-w-screen-xl"
  },
  "components/pages/features/layout-17.html": {
    "status": "ok",
    "checkedAt": "2026-03-11",
    "desktop": "ok",
    "mobile": "ok",
    "note": "gefixed: <div>\u2192<article>, container mx-auto px-6\u2192max-w-screen-xl"
  },
  "components/pages/features/layout-170.html": {
    "status": "ok",
    "checkedAt": "2026-03-11",
    "desktop": "ok",
    "mobile": "ok",
    "note": "gefixed: <div>\u2192<article>, container mx-auto px-6\u2192max-w-screen-xl"
  },
  "components/pages/features/layout-171.html": {
    "status": "ok",
    "checkedAt": "2026-03-11",
    "desktop": "ok",
    "mobile": "ok",
    "note": "gefixed: <div>\u2192<article>, container mx-auto px-6\u2192max-w-screen-xl"
  },
  "components/pages/features/layout-172.html": {
    "status": "ok",
    "checkedAt": "2026-03-11",
    "desktop": "ok",
    "mobile": "ok",
    "note": "gefixed: <div>\u2192<article>, container mx-auto px-6\u2192max-w-screen-xl"
  },
  "components/pages/features/layout-173.html": {
    "status": "ok",
    "checkedAt": "2026-03-11",
    "desktop": "ok",
    "mobile": "ok",
    "note": "gefixed: <div>\u2192<article>, container mx-auto px-6\u2192max-w-screen-xl; screenshot ok"
  }
}